salt_infisical/__about__.py
salt_infisical/__init__.py
salt_infisical-2.1.4.dist-info/METADATA
salt_infisical-2.1.4.dist-info/WHEEL
salt_infisical-2.1.4.dist-info/licenses/LICENSE
salt_infisical-2.1.4.dist-info/RECORD
