Metadata-Version: 2.3
Name: salt-infisical
Version: 2.1.4
Project-URL: Documentation, https://github.com/unknown/salt-infisical#readme
Project-URL: Issues, https://github.com/unknown/salt-infisical/issues
Project-URL: Source, https://github.com/unknown/salt-infisical
Author-email: Jonathan Treffler <mail@jonathan-treffler.de>
License-Expression: MIT
License-File: LICENSE
Classifier: Development Status :: 4 - Beta
Classifier: Programming Language :: Python
Classifier: Programming Language :: Python :: 3.7
Classifier: Programming Language :: Python :: 3.8
Classifier: Programming Language :: Python :: 3.9
Classifier: Programming Language :: Python :: 3.10
Classifier: Programming Language :: Python :: 3.11
Classifier: Programming Language :: Python :: Implementation :: CPython
Classifier: Programming Language :: Python :: Implementation :: PyPy
Requires-Python: >=3.7
Requires-Dist: infisical-python
